utilitz/__init__.py
utilitz/crypto.py
utilitz/excel.py
utilitz/io.py
utilitz/path.py
utilitz/regex.py
utilitz/sys.py
utilitz-0.7.4.dist-info/METADATA
utilitz-0.7.4.dist-info/WHEEL
utilitz-0.7.4.dist-info/licenses/LICENSE
utilitz-0.7.4.dist-info/RECORD
